<?xml version="1.0" encoding="utf-8" ?><dwsync><file name="about.htm" server="ftp.nicksblog.net//htdocs/" local="3375700320" remote="11966682272" /><file name="anchor.htm" server="ftp.nicksblog.net//htdocs/" local="3375700320" remote="11966682272" /><file name="charmap.htm" server="ftp.nicksblog.net//htdocs/" local="3375700320" remote="11966682272" /><file name="color_picker.htm" server="ftp.nicksblog.net//htdocs/" local="3375700320" remote="11966682272" /><file name="editor_template.js" server="ftp.nicksblog.net//htdocs/" local="3375700318" remote="11966682272" /><file name="editor_template_src.js" server="ftp.nicksblog.net//htdocs/" local="3375700318" remote="11966682272" /><file name="image.htm" server="ftp.nicksblog.net//htdocs/" local="3375700320" remote="11966682272" /><file name="link.htm" server="ftp.nicksblog.net//htdocs/" local="3375700320" remote="11966682272" /><file name="source_editor.htm" server="ftp.nicksblog.net//htdocs/" local="3375700320" remote="11966682272" /></dwsync>