<?xml version="1.0" encoding="utf-8" ?><dwsync><file name="swftools.admin.css" server="ftp.nicksblog.net//htdocs/" local="3342919440" remote="16261580868" /><file name=".cvsignore" server="ftp.nicksblog.net//htdocs/" local="3342919380" remote="16261580808" /><file name="swftools.admin.inc" server="ftp.nicksblog.net//htdocs/" local="3342919440" remote="16261580868" /><file name="swftools.admin.status.inc" server="ftp.nicksblog.net//htdocs/" local="3342919440" remote="16261580868" /><file name="swftools.info" server="ftp.nicksblog.net//htdocs/" local="3342919440" remote="16261580868" /><file name="swftools.install" server="ftp.nicksblog.net//htdocs/" local="3342919440" remote="16261580868" /><file name="genericplayers.module" server="ftp.nicksblog.net//htdocs/" local="3342919380" remote="16261580808" /><file name="swftools.module" server="ftp.nicksblog.net//htdocs/" local="3342919440" remote="16261580868" /><file name=".project" server="ftp.nicksblog.net//htdocs/" local="3342919380" remote="16261580808" /><file name="CHANGELOG.txt" server="ftp.nicksblog.net//htdocs/" local="3342919380" remote="16261580808" /><file name="INSTALL.txt" server="ftp.nicksblog.net//htdocs/" local="3342919380" remote="16261580808" /><file name="LICENSE.txt" server="ftp.nicksblog.net//htdocs/" local="3342919380" remote="16261580808" /></dwsync>